binlog-0.5.0.dist-info/METADATA
binlog-0.5.0.dist-info/WHEEL
binlog-0.5.0.dist-info/license_files/LICENSE
binlog/__init__.py
binlog/binlog.cpython-310-darwin.so
binlog-0.5.0.dist-info/RECORD
