Metadata-Version: 2.1
Name: binlog
Version: 0.5.0
Classifier: Programming Language :: Rust
Classifier: Programming Language :: Python :: Implementation :: CPython
Classifier: Programming Language :: Python :: Implementation :: PyPy
Requires-Dist: cffi
License-File: LICENSE
Summary: A binary data log library
Keywords: database
Author: Yusuf Simonson <simonson@gmail.com>
Author-email: Yusuf Simonson <simonson@gmail.com>
License: AGPL-3.0-or-later
Requires-Python: >=3.7
